woahdiscord/__init__.py
woahdiscord/discord_script.py
woahdiscord/file_jpg.py
woahdiscord/merge_chunk.py
woahdiscord/osmosis.py
woahdiscord/splitting_chunk.py
woahdiscord-0.1.2.dist-info/METADATA
woahdiscord-0.1.2.dist-info/WHEEL
woahdiscord-0.1.2.dist-info/top_level.txt
woahdiscord-0.1.2.dist-info/RECORD
