Metadata-Version: 2.1
Name: woahdiscord
Version: 0.1.2
Summary: A python library allowing discord to be used unlimited cloud storage. 
Author: TAWSIF AHMED
Author-email: sleeping4cat@outlook.com
Requires-Dist: discord
